{
  "timestamp": "2026-06-24T13:00:21Z",
  "date": "2026-06-24",
  "services": {
    "abdelrahman": {
      "name": "Abdelrahman Portfolio",
      "url": "https://www.abdelrahman-ezzat.com",
      "status": "up",
      "http_status": 200,
      "response_time_s": 0.074476
    },
    "website": {
      "name": "QuNeva Website",
      "url": "https://www.quneva.com",
      "status": "up",
      "http_status": 200,
      "response_time_s": 0.084611
    },
    "ha": {
      "name": "QuNeva HA",
      "url": "https://ha.quneva.com",
      "status": "up",
      "http_status": 200,
      "response_time_s": 0.539996
    },
    "ai": {
      "name": "QuNeva AI",
      "url": "https://ai.quneva.com",
      "status": "up",
      "http_status": 200,
      "response_time_s": 0.172479
    },
    "root": {
      "name": "QuNeva Root Domain",
      "url": "https://quneva.com",
      "status": "up",
      "http_status": 200,
      "response_time_s": 0.092194
    }
  }
}
