{
  "timestamp": "2026-07-05T09:01:01Z",
  "date": "2026-07-05",
  "services": {
    "abdelrahman": {
      "name": "Abdelrahman Portfolio",
      "url": "https://www.abdelrahman-ezzat.com",
      "status": "up",
      "http_status": 200,
      "response_time_s": 0.063479
    },
    "website": {
      "name": "QuNeva Website",
      "url": "https://www.quneva.com",
      "status": "up",
      "http_status": 200,
      "response_time_s": 0.062647
    },
    "ha": {
      "name": "QuNeva HA",
      "url": "https://ha.quneva.com",
      "status": "up",
      "http_status": 200,
      "response_time_s": 0.502185
    },
    "ai": {
      "name": "QuNeva AI",
      "url": "https://ai.quneva.com",
      "status": "up",
      "http_status": 200,
      "response_time_s": 0.063973
    },
    "root": {
      "name": "QuNeva Root Domain",
      "url": "https://quneva.com",
      "status": "up",
      "http_status": 200,
      "response_time_s": 0.061210
    }
  }
}
