{
  "timestamp": "2026-06-24T22:11:42Z",
  "date": "2026-06-24",
  "services": {
    "abdelrahman": {
      "name": "Abdelrahman Portfolio",
      "url": "https://www.abdelrahman-ezzat.com",
      "status": "up",
      "http_status": 200,
      "response_time_s": 0.108453
    },
    "website": {
      "name": "QuNeva Website",
      "url": "https://www.quneva.com",
      "status": "up",
      "http_status": 200,
      "response_time_s": 0.079888
    },
    "ha": {
      "name": "QuNeva HA",
      "url": "https://ha.quneva.com",
      "status": "up",
      "http_status": 200,
      "response_time_s": 0.695591
    },
    "ai": {
      "name": "QuNeva AI",
      "url": "https://ai.quneva.com",
      "status": "up",
      "http_status": 200,
      "response_time_s": 0.072866
    },
    "root": {
      "name": "QuNeva Root Domain",
      "url": "https://quneva.com",
      "status": "up",
      "http_status": 200,
      "response_time_s": 0.079777
    }
  }
}
